smallbench/__init__.py
smallbench/baselines/agents/core.py
smallbench/baselines/agents/react.py
smallbench/baselines/agents/react_ft_demo.py
smallbench/benchmarks/core.py
smallbench/benchmarks/bcb_a/abstractions.py
smallbench/benchmarks/bcb_a/aci.py
smallbench/benchmarks/bcb_a/bench.py
smallbench/benchmarks/bcb_a/contexts.py
smallbench/benchmarks/bcb_a/test.py
smallbench/benchmarks/first_pr/bench.py
smallbench/benchmarks/first_pr/test.py
smallbench/core/aci.py
smallbench/utilities/code/linter.py
smallbench/utilities/code/use_docker.py
smallbench/utilities/code/use_modal.py
smallbench-0.2.28.dist-info/METADATA
smallbench-0.2.28.dist-info/WHEEL
smallbench-0.2.28.dist-info/licenses/LICENSE
smallbench-0.2.28.dist-info/RECORD
