Metadata-Version: 2.3
Name: smallbench
Version: 0.2.28
Summary: Small Benchmarks for LM Agents
Project-URL: Homepage, https://github.com/yourusername/smallbench
Project-URL: Repository, https://github.com/yourusername/smallbench.git
Author-email: Josh Purtell <jmvpurtell@gmail.com>
License: MIT
License-File: LICENSE
Requires-Python: >=3.10
Requires-Dist: apropos-ai==0.4.5
Requires-Dist: ollama>=0.3.2
Requires-Dist: pylint>=3.3.1
Requires-Dist: synth-sdk>=0.2.19
Requires-Dist: zyk>=0.2.5
